pel/__init__.py
pel/_vendor/__init__.py
pel/_vendor/dateutil/__init__.py
pel/_vendor/dateutil/_common.py
pel/_vendor/dateutil/_version.py
pel/_vendor/dateutil/easter.py
pel/_vendor/dateutil/parser/__init__.py
pel/_vendor/dateutil/parser/_parser.py
pel/_vendor/dateutil/parser/isoparser.py
pel/_vendor/dateutil/relativedelta.py
pel/_vendor/dateutil/rrule.py
pel/_vendor/dateutil/tz/__init__.py
pel/_vendor/dateutil/tz/_common.py
pel/_vendor/dateutil/tz/_factories.py
pel/_vendor/dateutil/tz/tz.py
pel/_vendor/dateutil/tz/win.py
pel/_vendor/dateutil/tzwin.py
pel/_vendor/dateutil/utils.py
pel/_vendor/dateutil/zoneinfo/__init__.py
pel/_vendor/dateutil/zoneinfo/dateutil-zoneinfo.tar.gz
pel/_vendor/dateutil/zoneinfo/rebuild.py
pel/_vendor/graphlib/__init__.py
pel/_vendor/graphlib/graphlib.py
pel/_vendor/graphlib_backport-1.0.3.dist-info/INSTALLER
pel/_vendor/graphlib_backport-1.0.3.dist-info/METADATA
pel/_vendor/graphlib_backport-1.0.3.dist-info/RECORD
pel/_vendor/graphlib_backport-1.0.3.dist-info/REQUESTED
pel/_vendor/graphlib_backport-1.0.3.dist-info/WHEEL
pel/_vendor/python_dateutil-2.8.2.dist-info/INSTALLER
pel/_vendor/python_dateutil-2.8.2.dist-info/LICENSE
pel/_vendor/python_dateutil-2.8.2.dist-info/METADATA
pel/_vendor/python_dateutil-2.8.2.dist-info/RECORD
pel/_vendor/python_dateutil-2.8.2.dist-info/REQUESTED
pel/_vendor/python_dateutil-2.8.2.dist-info/WHEEL
pel/_vendor/python_dateutil-2.8.2.dist-info/top_level.txt
pel/_vendor/python_dateutil-2.8.2.dist-info/zip-safe
pel/console.py
pel/core.py
pel/datetime.py
pel/docker.py
pel/exceptions.py
pel/filesystem.py
pel/run.py
pel/tasks.py
pel/types.py
pel-0.0.1.dist-info/entry_points.txt
pel-0.0.1.dist-info/LICENSE
pel-0.0.1.dist-info/WHEEL
pel-0.0.1.dist-info/METADATA
pel-0.0.1.dist-info/RECORD
