Metadata-Version: 2.1
Name: pel
Version: 0.0.1
Summary: The most elegant build system.
Home-page: https://github.com/neocrym/pel
License: MIT
Author: Neocrym Records Inc.
Author-email: engineering@neocrym.com
Requires-Python: >=3.8,<3.11
Classifier: Development Status :: 4 - Beta
Classifier: License :: OSI Approved :: MIT License
Classifier: Programming Language :: Python :: 3
Classifier: Programming Language :: Python :: 3.10
Classifier: Programming Language :: Python :: 3.8
Classifier: Programming Language :: Python :: 3.9
Classifier: Topic :: Software Development :: Build Tools
Classifier: Topic :: Software Development :: Libraries :: Python Modules
Project-URL: Repository, https://github.com/neocrym/pel
